MANIFEST.in
runtests.py
setup.py
QVScriptTools.egg-info/PKG-INFO
QVScriptTools.egg-info/SOURCES.txt
QVScriptTools.egg-info/dependency_links.txt
QVScriptTools.egg-info/entry_points.txt
QVScriptTools.egg-info/top_level.txt
blocks/Default_Call_Meta.xml
blocks/Default_Init_Meta.xml
blocks/Default_Start.xml
blocks/Default_Sub_Meta.xml
blocks/Sub_Metadata.xml
blocks/Subbify_Main.xml
blocks/Subbify_SmartCall_Init.xml
blocks/Subbify_SmartCall_Run.xml
blocks/Subbify_Sub_Metadata.xml
blocks/Subbify_Template_End.xml
blocks/Subbify_Template_Mid.xml
blocks/Subbify_Template_Start.xml
docs/index.rst
docs/modules.rst
qvstools/__init__.py
qvstools/blocks.py
qvstools/log.py
qvstools/prj.py
qvstools/qvd.py
qvstools/regex_store.py
qvstools/subbify.py
qvstools/text.py
qvstools/tests/__init__.py
qvstools/tests/test_blocks.py
qvstools/tests/test_logfile.py
qvstools/tests/test_prj.py
qvstools/tests/test_qvd.py
qvstools/tests/test_subbify.py
qvstools/tests/test_text.py
qvstools/tests/testdata/DepsGraph1.qvw
qvstools/tests/testdata/DepsGraph1.qvw.log
qvstools/tests/testdata/DepsGraph2.qvw
qvstools/tests/testdata/DepsGraph2.qvw.log
qvstools/tests/testdata/DepsGraph3.qvw
qvstools/tests/testdata/DepsGraph3.qvw.log
qvstools/tests/testdata/DepsGraphTable1.qvd
qvstools/tests/testdata/DepsGraphTable2.qvd
qvstools/tests/testdata/DepsGraphTable3.qvd
qvstools/tests/testdata/ETLTubeData.qvs
qvstools/tests/testdata/ETLTubeData_Subbified.qvw
qvstools/tests/testdata/ETLTubeData_Subbified.qvw.log
qvstools/tests/testdata/Subbify_TestInput.qvs
qvstools/tests/testdata/Test.qvd
qvstools/tests/testdata/ETLTubeData_Subbified-prj/AllProperties.xml
qvstools/tests/testdata/ETLTubeData_Subbified-prj/CH01_238332217.xml
qvstools/tests/testdata/ETLTubeData_Subbified-prj/CH02_438168158.xml
qvstools/tests/testdata/ETLTubeData_Subbified-prj/DocBinary.dat
qvstools/tests/testdata/ETLTubeData_Subbified-prj/DocInternals.xml
qvstools/tests/testdata/ETLTubeData_Subbified-prj/DocProperties.xml
qvstools/tests/testdata/ETLTubeData_Subbified-prj/IB01_312372977.xml
qvstools/tests/testdata/ETLTubeData_Subbified-prj/LB01_694069076.xml
qvstools/tests/testdata/ETLTubeData_Subbified-prj/LoadScript.txt
