Metadata-Version: 1.1
Name: QVScriptTools
Version: 0.126.dev0
Summary: Tools for making Qlikview load scripts and doing other automation tasks on Qlikview projects.
Home-page: https://github.com/BenSimonds/Qlik-Script-Tools
Author: BenSimonds
Author-email: BSSimonds@gmail.com
License: UNKNOWN
Download-URL: https://github.com/BenSimonds/Qlik-Script-Tools/archive/master.zip
Platform: UNKNOWN
